motor_decorator/__init__.py
motor_decorator/abstract_view.py
motor_decorator/base_db.py
motor_decorator/controller.py
motor_decorator/exception.py
motor_decorator/objects.py
motor_decorator/profiler.py
motor_decorator/registrator.py
motor_decorator/settings.py
motor_decorator/tools.py
motor_decorator-0.0.3.8.dist-info/LICENSE
motor_decorator-0.0.3.8.dist-info/METADATA
motor_decorator-0.0.3.8.dist-info/WHEEL
motor_decorator-0.0.3.8.dist-info/top_level.txt
motor_decorator-0.0.3.8.dist-info/RECORD
