Metadata-Version: 2.1
Name: motor-decorator
Version: 0.0.3.8
Summary: Decorator for motor library
Home-page: https://github.com/FeltsAzn/motor-decorator
Author: Timur Galiev
Author-email: timkin12321@gmail.com
License: LICENSE
License-File: LICENSE
Requires-Dist: pydantic >=2.5.3
Requires-Dist: motor >=3.3.2
